landlab_triangle/__init__.py
landlab_triangle/graph.py
landlab_triangle/mesh.py
landlab_triangle/triangle.py
landlab_triangle-0.0.2.dist-info/METADATA
landlab_triangle-0.0.2.dist-info/WHEEL
landlab_triangle-0.0.2.dist-info/licenses/LICENSE
landlab_triangle-0.0.2.dist-info/RECORD
