Metadata-Version: 2.4
Name: landlab-triangle
Version: 0.0.2
Summary: Create unstructured Landlab grids using Jonathan Shewchuk's Triangle mesh generation software
Author-email: Ethan <ethan.g.pierce@dartmouth.edu>
License-Expression: MIT
License-File: LICENSE
Keywords: grid,landlab,mesh,triangle,unstructured
Classifier: License :: OSI Approved :: MIT License
Classifier: Operating System :: OS Independent
Classifier: Programming Language :: Python :: 3
Requires-Python: >=3.13
Requires-Dist: geopandas>=1.1.1
Requires-Dist: landlab>=2.10.1
Requires-Dist: shapely>=2.1.1
Requires-Dist: triangle
